Workbook

Sheet Data
A1: Published_Date | B1: City | C1: Crime_Type | D1: Accused | E1: Motive | F1: Method | G1: Deaths | H1: Injured | I1: Police_Action | J1: Victim_Details | K1: Summary | L1: Source_Name | M1: Source_URL | N1: Language | O1: City_Standard | P1: Crime_Category
A2: 45679 | B2: Karachi | C2: Honor Killing | D2: Fatima's father, Azhar | E2: So-called honour | F2: Shooting | G2: 2 | H2: 0 | I2: Arrested | J2: Fatima, teenage girl; Ali Solangi, 20 | K2: A teenage girl and her friend were shot dead in Karachi in an honor killing by the girl's father after discovering their relationship. | L2: Dawn News | M2: https://www.dawn.com/news/1886892 | N2: English | O2: Karachi | P2: Honor Killing
A3: 45667 | B3: Karachi | C3: Road Accident | D3: Water tanker driver | E3: Negligence | F3: Ran over by water tanker | G3: 2 | H3: 1 | I3: Report sought from Sindh Inspector General of Police | J3: 2 deceased, ages 57 and 49; 1 injured, age 30 | K3: Two people were killed and one injured when a water tanker ran over them on Shaheed-i-Millat Road in Karachi. The victims were taken to Jinnah Postgraduate Medical Centre. | L3: Dawn News | M3: https://www.dawn.com/news/1884293/2-killed-1-injured-in-water-tanker-accident-on-karachis-shaheed-i-millat-road-authorities | N3: English | O3: Karachi | P3: Accident / Hit & Run
A4: 45678 | B4: Karachi | C4: Robbery | D4: 3 armed robbers, 1 arrested suspect | E4: Not specified | F4: Shoot-out | G4: 2 | H4: 3 | I4: Police patrol arrived, 1 suspect arrested | J4: Jehanzeb Ibrahim, Subhan Ibrahim, Khurram, Muhammad Zubair | K4: Two suspected robbers were shot dead during a shoot-out with police in North Karachi, while three citizens were wounded. In a separate incident, a young man named Muhammad Zubair was shot dead in Gulshan-i-Iqbal. | L4: Dawn News | M4: https://www.dawn.com/news/1886644 | N4: English | O4: Karachi | P4: Robbery / Theft
A5: 45669 | B5: Karachi | C5: Murder | D5: Asma, Ghulam Nabi alias Deedar | E5: To get rid of her husband | F5: Strangulation and electrocution | G5: 1 | H5: 0 | I5: Court sentenced the accused | J5: Shah Zaman | K5: A sessions court sentenced Asma to life in prison for murdering her husband, Shah Zaman, with the help of co-accused Ghulam Nabi, who was sentenced to death. The murder was staged as a suicide. | L5: Dawn News | M5: https://www.dawn.com/news/1884601 | N5: English | O5: Karachi | P5: Murder
A6: 45680 | B6: Karachi | C6: Murder | D6: Rameez, accomplice | E6: Ransom | F6: Kidnapping and murder | G6: 1 | H6: 0 | I6: FIR registered, suspect arrested | J6: Iqbal Ahmed, 34M | K6: Iqbal Ahmed, who was kidnapped for ransom, was found murdered in his apartment. The police arrested a suspect who confessed to the crime. | L6: Dawn News | M6: https://www.dawn.com/news/1887063 | N6: English | O6: Karachi | P6: Murder
A7: 45675 | B7: Karachi | C7: Child Abduction and Murder | D7: Unknown | E7: Not specified | F7: Abduction and suspected homicide | G7: 1 | H7: 0 | I7: Investigation underway, body sent for postmortem, special investigation team formed | J7: Mohammed Sarim, 7 years old | K7: A seven-year-old boy, Mohammed Sarim, was found dead in a water tank after being missing for over a week. The police suspect foul play due to multiple injuries on the body, and investigations are ongoing. | L7: Dawn News | M7: https://www.dawn.com/news/1886087 | N7: English | O7: Karachi | P7: Child Abuse / Abduction
A8: 45668 | B8: Karachi | C8: Traffic Accident | D8: Shahzad Ali Shah (tanker driver) | E8: Rash driving | F8: Hit and run by water tanker | G8: 3 | H8: 1 | I8: Case registered against the tanker driver | J8: Syed Noman, Israr Ahmed, Saeed | K8: Three people were killed in two separate incidents involving water tankers in Karachi. The first incident involved an angry mob setting a tanker on fire after it hit two motorcyclists, while the second incident resulted in the death of a bike rider. | L8: Dawn News | M8: https://www.dawn.com/news/1884462 | N8: English | O8: Karachi | P8: Accident / Hit & Run
A9: 45682 | B9: Karachi | C9: Accidental Death | D9: Tariq Khan | F9: Car accident | G9: 1 | H9: 1 | I9: Investigation ongoing | J9: Danish, traffic marshal | K9: A track marshal named Danish was killed during the Hub Rally Autocross in Karachi when a car lost control and hit him, dragging him into a ditch. | L9: Dawn News | M9: https://www.dawn.com/news/1887608 | N9: English | O9: Karachi | P9: Accident / Hit & Run
A10: 45678 | B10: Karachi | C10: Child Abuse | D10: Teacher of the seminary | E10: Sexual assault | F10: Murder after sexual assault | G10: 1 | H10: 0 | I10: Suspect in custody, DNA samples being taken | J10: Mohammed Sarim, 7M | K10: The body of a seven-year-old boy, Mohammed Sarim, was found in a water tank after he went missing for 11 days. A post-mortem confirmed he was sexually assaulted before being killed, leading police to treat the case as murder. | L10: Dawn News | M10: https://www.dawn.com/news/1886645 | N10: English | O10: Karachi | P10: Child Abuse / Abduction
A11: 45672 | B11: Karachi | C11: Murder | D11: Uzair Baloch and his accomplices | E11: Not specified | F11: Police encounter | G11: 2 | H11: 0 | I11: Acquitted by court | J11: Constable Muhammad Asif, passer-by Nisar Ahmed | K11: Uzair Baloch, chief of the outlawed Peoples Amn Committee, was acquitted in a double murder case involving Constable Muhammad Asif and passer-by Nisar Ahmed due to lack of evidence. | L11: Dawn News | M11: https://www.dawn.com/news/1885190 | N11: English | O11: Karachi | P11: Murder
A12: 45658 | B12: Karachi | C12: Aerial Firing | D12: 75 suspects arrested | E12: Celebratory | F12: Aerial gunfire | G12: 0 | H12: 26 | I12: Further investigations underway | J12: Various ages and locations, including an 11-year-old boy and a 35-year-old male | K12: Aerial firing during New Year���s celebrations in Karachi injured 26 people, with 75 suspects arrested for celebratory gunfire. | L12: Dawn News | M12: https://www.dawn.com/news/1882435 | N12: English | O12: Karachi | P12: Assault / Firing
A13: 45680 | B13: Karachi | C13: Kidnapping/Murder | D13: Couple riding a motorcycle | E13: Sexual assault | F13: Kidnapping and murder | G13: 1 | H13: 0 | I13: Police treating the matter as a murder case, patrolling enhanced | J13: Third child, found dead in underground water tank | K13: Three children were kidnapped in Karachi, with one found dead after being sexually assaulted. Police are treating the case as a murder. | L13: Dawn News | M13: https://www.dawn.com/news/1887223 | N13: English | O13: Karachi | P13: Murder
A14: 45685 | B14: Sanghar | C14: Armed Assault | D14: MNA Allauddin Junejo and his armed men | E14: Land occupation | F14: Gunned down | G14: 3 | H14: 15 | I14: FIR not registered against MNA | J14: Mushtaq Junejo, Ali Baksh Junejo, Abdul Rasool Junejo | K14: Three men were killed and over a dozen injured in an armed assault in Sanghar. Protests erupted as police refused to name MNA Junejo in the FIR. | L14: Express Tribune | M14: https://tribune.com.pk/story/2524935/sanghar-police-accused-of-shielding-ppp-mna-in-triple-murder-case | N14: English | O14: Sanghar | P14: Assault / Firing
A15: 45667 | B15: Karachi | C15: Traffic Accident | D15: Driver of the tanker (fled the scene) | F15: Collision with motorcycles | G15: 2 | H15: 1 | I15: Investigation initiated | J15: Jamil, 44 years old; Muhammad Akbar, 30 years old | K15: Two motorcyclists were killed and one injured in a traffic accident on Shaheed-e-Millat Road when a water tanker collided with their motorcycles. The driver fled the scene. | L15: Express Tribune | M15: https://tribune.com.pk/story/2521246/water-tanker-crushes-two-motorcyclists-to-death-in-karachi | N15: English | O15: Karachi | P15: Accident / Hit & Run
A16: 45659 | B16: Lodhran | C16: Murder | D16: Unidentified assailant | E16: Not specified | F16: Shooting | G16: 1 | H16: 0 | I16: Case registered, investigation initiated | J16: Shakeel Ahmed, resident of Liaquatpur, Rahim Yar Khan | K16: A trailer driver, Shakeel Ahmed, was shot dead by an unidentified assailant in Lodhran while transporting goods from Karachi to Rawalpindi. Police have registered a case and are investigating the incident. | L16: Express Tribune | M16: https://tribune.com.pk/story/2519560/fugitive-killed-in-police-encounter | N16: English | O16: Lodhran | P16: Murder
A17: 45671 | B17: Swabi | C17: Honor Killing | D17: Husband | E17: Honor | F17: Shooting | G17: 2 | H17: 1 | I17: FIR registered | J17: 26-year-old woman | K17: A man allegedly killed his wife for honor and later died by suicide in Chota Lahor tehsil. The incident involved a shooting where the husband shot his wife and then himself. | L17: Dawn News | M17: https://www.dawn.com/news/1885068 | N17: English | O17: Swabi | P17: Honor Killing
A18: 45659 | B18: Bakr Jamali | C18: Honor Killing | D18: Husband of the victim | E18: Greed for money and property, claimed 'honour' | F18: Brutal murder | G18: 1 | H18: 0 | I18: Culprit arrested | J18: Young female lecturer and mother of three | K18: A young female lecturer was brutally murdered by her husband in an honor killing incident in Bakr Jamali, Sindh. The husband admitted to the crime, claiming it was out of 'honour', while the victim's family alleged greed for money and property. | L18: Dawn News | M18: https://www.dawn.com/news/1882572 | N18: English | O18: Bakr Jamali | P18: Honor Killing
A19: 45661 | B19: Peshawar | C19: Firing Incident | D19: Unidentified suspects | E19: Personal enmity over property and previous murders | F19: Exchange of fire | G19: 5 | H19: 6 | I19: Search for fleeing suspects | J19: People returning from a wedding ceremony | K19: Firing between two parties in Peshawar's Tehkal area resulted in five deaths and six injuries, stemming from personal enmity over property disputes. | L19: Dawn News | M19: https://www.dawn.com/news/1883049 | N19: English | O19: Peshawar | P19: Assault / Firing
A20: 45661 | B20: Turbat | C20: Terrorism | D20: Balochistan Liberation Army | E20: Terrorism | F20: Blast targeting a bus | G20: 4 | H20: 32 | I20: Investigations being conducted, area cordoned off by police and security forces | J20: Passengers on the bus, including SSP Zohaib Mohsin and his family | K20: A blast targeting a bus in Turbat resulted in 4 deaths and 32 injuries. The Balochistan Liberation Army claimed responsibility for the attack. | L20: Dawn News | M20: https://www.dawn.com/news/1883061 | N20: English | O20: Turbat | P20: Terrorism
A21: 45664 | B21: Islamabad | C21: Murder | D21: Unknown | E21: Not clear | F21: Found dead with injuries | G21: 1 | H21: 0 | I21: Body shifted to hospital | J21: Thomas Jurgen Bielefeld, 58, German diplomat | K21: A German diplomat, Thomas Jurgen Bielefeld, was found dead in his residence in Islamabad's Diplomatic Enclave with injuries. The police are investigating the circumstances surrounding his death. | L21: Dawn News | M21: https://www.dawn.com/news/1883542 | N21: English | O21: Islamabad | P21: Murder
A22: 45686 | B22: Sanghar | C22: Murder | D22: Salahuddin Junejo, Mohammed Khan Junejo, others | E22: Trespassing of cattle | F22: Gunfire | G22: 3 | H22: 19 | I22: FIR not registered | J22: Three members of Junejo community | K22: Three people were killed and 19 others injured in a clash between two groups over cattle trespassing in Sanghar. Protesters demand FIR against the accused, including a PPP lawmaker. | L22: Dawn News | M22: https://www.dawn.com/news/1888314 | N22: English | O22: Sanghar | P22: Murder
A23: 45675 | B23: Kurram | C23: Murder, Terrorism | D23: Unidentified militants | E23: Violations of peace agreement | F23: Ambush, IED blast | G23: 6 | H23: 7 | I23: Search operation launched, retaliatory action by security forces | J23: 4 drivers, identified as Imran, Hasan Ali, Shahid Ali; 1 FC soldier, Havildar Tasnim | K23: An ambush on a convoy in Lower Kurram resulted in the deaths of four drivers and two security officials, with several others injured. The attack was linked to ongoing tensions despite a peace agreement. | L23: Dawn News | M23: https://www.dawn.com/news/1885970 | N23: English | O23: Kurram | P23: Terrorism
A24: 45672 | B24: Karachi | C24: Murder | D24: Uzair Baloch, Jibrail, Hafeez Dada, Babar Punjabi, Zubair, Basir, Zahoor | E24: Not specified | F24: Shootout with police | G24: 2 | H24: 2 | I24: FIR lodged, acquitted by court | J24: Police officer Muhammad Asif, private individual Nisar Ahmed | K24: Uzair Baloch was acquitted in a case related to a police encounter that resulted in the deaths of two individuals in 2009. The court found insufficient evidence against him. | L24: The News International | M24: https://www.thenews.com.pk/print/1272309-uzair-baloch-acquitted-in-double-murder-case-for-want-of-evidence | N24: English | O24: Karachi | P24: Murder
A25: 45668 | B25: Mandi Bahauddin | C25: Explosion | D25: 2 people preparing fireworks | E25: Not specified | F25: Explosion due to short circuit | G25: 6 | H25: 7 | I25: Further investigation underway | J25: 6 deceased (1 man, 3 women, 2 girls), 7 injured (4 men, 3 women) | K25: An explosion at a firework warehouse in Mandi Bahauddin led to the roof of a house collapsing, resulting in 6 deaths and 7 injuries. | L25: Dawn News | M25: https://www.dawn.com/news/1884509 | N25: English | O25: Mandi Bahauddin | P25: Terrorism
A26: 45679 | B26: Islamabad | C26: Murder | D26: Iftikhar Ahmed, Muhammad Mustafa | E26: Police brutality | F26: Fatal shooting | G26: 1 | H26: 0 | I26: Death sentences reduced to life imprisonment | J26: Osama Satti, young man | K26: The Islamabad High Court reduced the death sentences of two police convicts in the Osama Satti murder case to life imprisonment while acquitting three others. Osama was fatally shot by police officers during an incident in January 2021. | L26: Express Tribune | M26: https://tribune.com.pk/story/2523749/ihc-reduces-death-penalties-to-life-imprisonment-in-osama-satti-case | N26: English | O26: Islamabad | P26: Murder
A27: 45687 | B27: North Waziristan | C27: Terrorism | D27: 6 khwarij (members of Tehreek-i-Taliban Pakistan) | E27: Terrorism | F27: Intelligence-based operation (IBO) | G27: 2 | H27: 0 | I27: Sanitisation operations conducted | J27: Major Hamza Israr, 29, Rawalpindi; Sepoy Muhammad Naeem, 26, Naseerabad | K27: Two soldiers were martyred and six terrorists were killed in an intelligence-based operation in North Waziristan. The operation targeted members of the banned Tehreek-i-Taliban Pakistan. | L27: Dawn News | M27: https://www.dawn.com/news/1888630 | N27: English | O27: North Waziristan | P27: Terrorism
... A57: 45682 | B57: Bahawalpur | C57: Kidnapping and Gang Rape | D57: Ishtiaq, Imran, Shehbaz | E57: Not specified | F57: Kidnapping and gang-rape | G57: 0 | H57: 0 | I57: Police raid conducted, victim recovered, case registered against accused | J57: Married woman, referred to as ���S��� | K57: A married woman was allegedly kidnapped by her relatives and sold to dacoits, where she was gang-raped. Police recovered her during a raid and handed her over to her family. | L57: Dawn News | M57: https://www.dawn.com/news/1887448 | N57: English | O57: Bahawalpur | P57: Rape / Sexual Assault
A58: 45675 | B58: Islamabad | C58: Corruption | D58: Imran Khan, Bushra Bibi, Malik Riaz | E58: Financial gain | F58: Misuse of authority, fraud | G58: 0 | H58: 0 | I58: Conviction announced | K58: Imran Khan and his wife Bushra Bibi were convicted in a corruption case involving the Al-Qadir Trust, with accusations of financial misconduct and misuse of authority. | L58: Dawn News | M58: https://www.dawn.com/news/1885973 | N58: English | O58: Islamabad | P58: Fraud / Corruption
A59: 45664 | B59: Khairpur | C59: Tribal Clash | D59: Armed men of Narejo tribe | E59: Tribal rivalry | F59: Open fire | G59: 2 | H59: 2 | I59: 119 criminals arrested in raids | K59: A tribal clash near Kalhora Kot resulted in the deaths of two individuals, Yameen Solangi and Sanaullah Solangi, due to gunfire from the Narejo tribe. The police have arrested 119 criminals in various operations. | L59: Express Tribune | M59: https://tribune.com.pk/story/2520501/ongoing-tribal-clashes-leave-two-more-dead | N59: English | O59: Khairpur | P59: Mob / Sectarian Violence
A60: 45674 | B60: Fateh Jang | C60: Robbery | D60: Hikmatullah, Sabit Khan, Milad Pasran Akhmat Gull | E60: Financial gain | F60: Snatching at gunpoint | G60: 0 | H60: 0 | I60: Case registered, suspects arrested, physical remand obtained | J60: Muhammad Bilal, citizen | K60: Police arrested three members of an Afghan gang involved in robbing citizens. The suspects snatched a mobile phone and Rs84,000 from the victim at gunpoint. | L60: Express Tribune | M60: https://tribune.com.pk/story/2522604/gang-of-afghan-bandits-busted | N60: English | O60: Fateh Jang | P60: Robbery / Theft
A61: 45684 | B61: Karachi | C61: Robbery | D61: Waqar Younas, Mubarak Shah | E61: Financial gain | F61: Forcibly covering heads and tying hands | G61: 0 | H61: 0 | I61: Case registered, suspects arrested, van seized, illegal weapons recovered | J61: Muhammad Ismail, livestock trader, Rs430,500 looted; Muhammad Anwar, passenger, Rs310,000 looted | K61: Saddar police arrested ringleader Waqar Younas and accomplice Mubarak Shah of a robbers' gang involved in looting passengers in a van. The suspects forcibly tied the victims and stole cash and a mobile phone. | L61: Express Tribune | M61: https://tribune.com.pk/story/2524709/two-netted-for-robbing-passengers | N61: English | O61: Karachi | P61: Robbery / Theft
A62: 45679 | B62: Karachi | C62: Robbery | D62: Mohammad Shariful Islam Shehzad | E62: Robbery | F62: Stabbing | G62: 0 | H62: 1 | I62: Suspect apprehended after a three-day manhunt | J62: Saif Ali Khan, actor | K62: Saif Ali Khan was attacked during a robbery attempt at his home, sustaining multiple stab wounds. He was rushed to the hospital by auto-rickshaw driver Bhajan Singh Rana, who responded to his distress call. | L62: Express Tribune | M62: https://tribune.com.pk/story/2523778/saif-ali-khan-poses-with-auto-driver-who-rushed-him-to-hospital | N62: English | O62: Karachi | P62: Robbery / Theft
A63: 45679 | B63: Karachi | C63: Terrorism | D63: Unidentified gunmen | E63: Sectarian tensions | F63: Rocket attack and abduction | G63: 6 | H63: 7 | I63: Operation against miscreants initiated | J63: Members of a convoy carrying essential items | K63: A convoy was attacked by unidentified gunmen near Bagan, resulting in the abduction of several individuals and the discovery of six dead bodies later. The authorities have launched an operation against the miscreants. | L63: Express Tribune | M63: https://tribune.com.pk/story/2523691/people-in-bagan-start-surrendering-firearms | N63: English | O63: Karachi | P63: Terrorism
A64: 45681 | B64: Karachi | C64: Violence during protest | D64: Sanan Khan Qureshi and 43 others | E64: Protest against Bahria Town Karachi | F64: Chanting anti-state slogans, resorting to violence, ransacking, torching private properties | G64: 0 | H64: 0 | I64: Two FIRs lodged, trial conducted | J64: Not specified | K64: An anti-terrorism court exonerated Sanan Khan Qureshi and 43 others from charges of violence during a protest against Bahria Town Karachi in 2021, citing lack of evidence. | L64: The News International | M64: https://www.thenews.com.pk/print/1275418-jsqm-leader-acquitted-in-bahria-town-violence-cases-for-lack-of-evidence | N64: English | O64: Karachi | P64: Mob / Sectarian Violence
A65: 45662 | B65: Muzaffargarh | C65: Robbery | D65: Unidentified robbers | E65: Robbery | F65: Shooting | G65: 1 | H65: 0 | I65: FIR registered, investigation underway | J65: Adil Gadi, trader | K65: A trader named Adil Gadi was shot dead by robbers near Noor Shah Talai when he resisted their demands for valuables. Local police have registered a case and are investigating the incident. | L65: The Nation | M65: https://www.nation.com.pk/05-Jan-2025/trader-shot-dead-for-resisting-robbery-in-muzaffargarh | N65: English | O65: Muzaffargarh | P65: Robbery / Theft
A66: 45674 | B66: Karachi | C66: Assault | D66: Jawad Ahmad and his men | E66: Power theft | F66: Thrashed officials and snatched faulty meter | G66: 0 | H66: 2 | I66: Application submitted for registration of a case, police asked to settle the issue | J66: Officials of Lahore Electric Supply Company (Lesco) | K66: Singer Jawad Ahmad and his men allegedly assaulted officials from Lesco after they detected power theft at a beauty salon owned by the singer's wife, leading to a request for police action. | L66: Dawn News | M66: https://images.dawn.com/news/1193148/legal-action-sought-after-jawad-ahmad-beats-harasses-lesco-staff-outside-wifes-salon | N66: English | O66: Karachi | P66: Assault / Firing
A67: 45687 | B67: Karachi | C67: Robbery | D67: Unidentified assailants | E67: Robbery | F67: Violent attack | G67: 0 | H67: 1 | I67: Investigation ongoing | J67: Saif Ali Khan, actor | K67: Saif Ali Khan was attacked at his home during an alleged robbery attempt, resulting in serious injuries that required immediate surgery. | L67: Express Tribune | M67: https://tribune.com.pk/story/2525476/karan-johar-announces-ibrahim-ali-khans-debut | N67: English | O67: Karachi | P67: Robbery / Theft
A68: 45671 | B68: Karachi | C68: Cryptocurrency Heist | D68: Eight suspects including police officers | E68: Financial gain | F68: Kidnapping and robbery | G68: 0 | H68: 0 | I68: Eight suspects arrested, investigation ongoing | J68: Muhammad Arsalan Malik, cryptocurrency trader | K68: Eight suspects, including police officers, were arrested in Karachi for a cryptocurrency heist worth over Rs90 million, involving the kidnapping of trader Muhammad Arsalan Malik. | L68: Express Tribune | M68: https://tribune.com.pk/story/2522025/eight-arrested-in-karachi-crypto-heist-rs129-million-recovered | N68: English | O68: Karachi | P68: Kidnapping
A69: 45658 | B69: Karachi | C69: Street Crime | D69: Ruthless street criminals | E69: Financial gain | F69: Robbery at gunpoint | G69: 106 | H69: 300 | I69: Police claimed a 21 percent reduction in crimes, but street crime continues to be a challenge | J69: Residents of Karachi, including women, children, and law-enforcement officials | K69: In 2024, Karachi experienced rampant street crime, resulting in 106 deaths and 300 injuries. Despite police claims of reduced crime rates, street criminals continued to operate with impunity, robbing residents of billions. | L69: The News International | M69: https://www.thenews.com.pk/print/1267450-karachi-saw-over-72-000-street-crime-incidents-in-2024 | N69: English | O69: Karachi | P69: Robbery / Theft
A70: 45673 | B70: Karachi | C70: Child Kidnapping | D70: Couple riding a motorcycle | E70: Ransom | F70: Abduction | G70: 0 | H70: 0 | I70: Investigation ongoing, case transferred to Anti-Violence Crime Cell | J70: Five-year-old Aliyan, six-year-old Ali Raza, seven-year-old Mohammed Sarim | K70: Three children have been kidnapped in Karachi, with ransom demands reported for one of them. The police are actively investigating the cases and have assured the families of their recovery. | L70: Dawn News | M70: https://www.dawn.com/news/1885683 | N70: English | O70: Karachi | P70: Child Abuse / Abduction
A71: 45669 | B71: Karachi | C71: Kidnapping | D71: Mohammed Rizwan Shah, Tariq Hasan Shah, 8 suspects including 2 constables of the Counter Terrorism Department | E71: Extortion | F71: Kidnapping for ransom | G71: 0 | H71: 0 | I71: Case registered, suspects arrested, identification parade conducted | J71: Crypto trader | K71: A crypto trader was kidnapped and released after paying a ransom of $340,000 in digital coins. Two suspects were identified during a parade, and eight suspects, including two police constables, were arrested for their involvement. | L71: Dawn News | M71: https://www.dawn.com/news/1884605 | N71: English | O71: Karachi | P71: Kidnapping
... A103: 45683 | B103: Muzaffarabad | C103: Sexual Assault | D103: 2 suspects | E103: Threat and intimidation | F103: Rape and filming the act | G103: 0 | H103: 1 | I103: FIR registered, suspect arrested, raid conducted | J103: 22-year-old girl | K103: In Muzaffarabad, police arrested one suspect involved in the sexual assault of a 22-year-old girl at her home. The suspects threatened the victim with a knife and filmed the assault. | L103: Dawn News | M103: https://www.dawn.com/news/1887654 | N103: English | O103: Muzaffarabad | P103: Rape / Sexual Assault
A104: 45682 | B104: Karachi | C104: Police Brutality | D104: Sindh Police | E104: Suppression of dissent | F104: Baton charges, arrests | G104: 0 | H104: Multiple | I104: Protesters arrested, police crackdown | J104: Sammi Deen Baloch, Fozia Baloch, Lala Wahab Baloch, Qazi Aman | K104: On January 18, 2025, a police crackdown on a Baloch rally in Lyari resulted in multiple arrests and reports of police brutality, including the assault of female activists. The incident highlights ongoing repression faced by the Baloch community. | L104: Express Tribune | M104: https://tribune.com.pk/article/97891/baloch-voices-silenced-a-tale-of-repression-in-lyari | N104: English | O104: Karachi | P104: Assault / Firing
A105: 45681 | B105: Karachi | C105: Cybercrime | D105: Group admin of WhatsApp group | E105: Spreading chaos among the public | F105: Uploading an immoral, insulting post on social media | G105: 0 | H105: 0 | I105: Arrested | J105: Punjab Chief Minister Maryam Nawaz | K105: The administrator of a WhatsApp group in Pakpattan was arrested for violating the Prevention of Electronic Crimes Act by allowing an insulting post about Punjab Chief Minister Maryam Nawaz to be shared in the group. | L105: Dawn News | M105: https://www.dawn.com/news/1887414 | N105: English | O105: Karachi | P105: Cybercrime
A106: 45685 | B106: Lahore | C106: Burglary | D106: Sana (wife of Humayun), Anam (wife of Nader Masih), Shahnaz (wife of Javed Masih), Shaiba (daughter of Humayun) | E106: Financial gain | F106: Home burglary | G106: 0 | H106: 0 | I106: Four women arrested, Rs60 million recovered | J106: Not specified | K106: Police arrested four women involved in a major home burglary in Lahore���s Model Town, recovering Rs60 million in cash and stolen items worth an additional Rs30 million. | L106: Express Tribune | M106: https://tribune.com.pk/story/2525049/four-women-arrested-for-home-theft-in-lahore-valuables-worth-rs90m-recovered | N106: English | O106: Lahore | P106: Robbery / Theft
A107: 45673 | B107: Lahore | C107: Terrorism | D107: Dr Zulqernain Butt | E107: Aggressive behaviour | F107: Opened fire on school buses | G107: 0 | H107: 0 | I107: FIR registered, suspect arrested | J107: Students in school buses | K107: A doctor was arrested for allegedly opening fire on two school buses in Lahore. No injuries were reported, and an FIR was filed under anti-terrorism and attempted murder charges. | L107: Dawn News | M107: https://www.dawn.com/news/1885600 | N107: English | O107: Lahore | P107: Terrorism
A108: 45671 | B108: Karachi | C108: Drug Smuggling | D108: Ugandan woman, Nigerian accomplice | E108: Financial gain | F108: Smuggling drugs in body capsules | G108: 0 | H108: 0 | I108: Suspect arrested, case registered under Narcotics Control Act | K108: The Anti-Narcotics Force arrested a Ugandan woman at Karachi Airport for attempting to smuggle drugs. She had drug-filled capsules inside her body and was connected to a Nigerian accomplice in Lahore. | L108: Express Tribune | M108: https://tribune.com.pk/story/2522009/ugandan-woman-arrested-for-drug-smuggling-at-karachi-airport | N108: English | O108: Karachi | P108: Drugs
A109: 45682 | B109: Karachi | C109: False FIR | D109: Unnamed individuals | E109: Defamation | F109: Arrest without clear explanation | G109: 0 | H109: 0 | I109: Arrested | J109: Zulqarnain Sikandar, TikToker | K109: TikToker Zulqarnain Sikandar was arrested during a friend's wedding, claiming he was held for hours without explanation due to false FIRs filed against him. | L109: Express Tribune | M109: https://tribune.com.pk/story/2524429/tiktoker-zulqarnain-sikandar-claims-unjustified-police-arrest-in-lahore | N109: English | O109: Karachi | P109: Police Action / Arrests
A110: 45667 | B110: Lodhran | C110: Objectionable Activities | D110: Abdul Rehman | E110: Exploitation of devotees | F110: Making videos of women | G110: 0 | H110: 0 | I110: Arrested by Basti Malook Police Station | J110: Women devotees | K110: A fake pir named Abdul Rehman was arrested by the Basti Malook Police for allegedly engaging in objectionable activities with his women devotees and making videos of them. | L110: Dawn News | M110: https://www.dawn.com/news/1884173 | N110: English | O110: Lodhran | P110: Fraud / Corruption
A111: 45669 | B111: Karak | C111: Traffic Accident | D111: Samiullah, trailer driver | E111: Brake failure | F111: Trailer fell over passenger coach | G111: 9 | H111: 13 | I111: Driver arrested and shifted to hospital | J111: Mohammad Ishaq, 59; Awam Khan, 45; Asma, 24; Naila, 3; Qaisar Khan, 30; Sharafat Ali; Salim Khan, 65; Qadir, 56; unidentified person | K111: Nine people died and a dozen were injured in a tragic road accident in Karak district when a trailer lost control and fell over a passenger coach. | L111: Dawn News | M111: https://www.dawn.com/news/1884583 | N111: English | O111: Karak | P111: Accident / Hit & Run
A112: 45688 | B112: Sanghar | C112: Clash | D112: 29 suspects including Chotiyaron police station SHO Ghulam Mohammad Sehto, Attaullah Junejo, Saifullah Junejo, Ali Hassan Junejo, Imamudin Rajar, Babu Keerio, Obhayo Rajar, Janu Landar and others | E112: Trespassing of cattle into fields | F112: Clash between two groups | G112: 3 | H112: 19 | I112: FIR registered, 9 suspects arrested | K112: A clash between two groups of the Junejo clan in Jani Junejo village resulted in the deaths of three men and injuries to nineteen others. Following negotiations, an FIR was registered against 29 suspects, and nine were arrested. | L112: Dawn News | M112: https://www.dawn.com/news/1888725 | N112: English | O112: Sanghar | P112: Mob / Sectarian Violence
A113: 45685 | B113: Karachi | C113: Financial Fraud | D113: Bright Star Business, Moonlight Traders | E113: Financial gain | F113: Suspicious transactions, over-invoicing | G113: 0 | H113: 0 | I113: 3 individuals arrested, currently out on bail | K113: A Senate subcommittee has ordered an audit of solar panel imports after discovering Rs70 billion in financial irregularities involving two companies. Three individuals have been arrested in connection with the scandal. | L113: Dawn News | M113: https://www.dawn.com/news/1888149 | N113: English | O113: Karachi | P113: Fraud / Corruption
A114: 45670 | B114: Gujrat | C114: Murder | D114: Azaan and accomplices; Asif | E114: Enmity; Domestic issue | F114: Gunfire | G114: 2; 1 | H114: 0 | I114: Case registered; Investigation started; Raiding parties constituted; 2 suspects arrested | J114: Zain Ali, 22; Ali Shan, 23; Ansa Bibi | K114: Two cousins were shot dead over enmity during a cricket match in Gujrat. Separately, a man shot his wife dead over a domestic issue. | L114: Dawn News | M114: https://www.dawn.com/news/1884796 | N114: English | O114: Gujrat | P114: Murder
A115: 45680 | B115: Haripur | C115: Human Trafficking | D115: Sheryar Ahmed | E115: Financial gain | F115: Illegal travel via boat | G115: 0 | H115: 0 | I115: Suspect arrested, raids conducted | J115: Not specified | K115: The FIA's Cybercrime Wing arrested Sheryar Ahmed, a human trafficker involved in the Greece boat incident, during a raid. Evidence was recovered from his mobile phone, and further raids are ongoing to apprehend the mastermind of the trafficking operation. | L115: Dawn News | M115: https://www.dawn.com/news/1887052 | N115: English | O115: Haripur | P115: Human Trafficking
A116: 45659 | B116: Karachi | C116: Tax Fraud | D116: Branch manager of the First Women Bank, Imperial Court Branch, Karachi | E116: Financial gain | F116: Aiding and abetting in a sales tax fraud case | G116: 0 | H116: 0 | I116: FIR registered | J116: Federal Board of Revenue (FBR) | K116: The Islamabad High Court granted bail to a bank manager accused of aiding in a Rs40b tax fraud case. The court found no material evidence implicating the petitioner in the alleged fraud. | L116: Dawn News | M116: https://www.dawn.com/news/1882504 | N116: English | O116: Karachi | P116: Fraud / Corruption
A117: 45674 | B117: Rawalpindi | C117: Corruption | D117: Imran Khan, Bushra Bibi | E117: Political victimization | F117: Conviction in corruption case | G117: 0 | H117: 0 | I117: Convicts taken into custody | K117: Former Prime Minister Imran Khan and his wife Bushra Bibi were convicted in a corruption case involving the Al-Qadir Trust, receiving 14 and 7 years in prison respectively, amid claims of political victimization. | L117: Dawn News | M117: https://www.dawn.com/news/1885831 | N117: English | O117: Rawalpindi | P117: Fraud / Corruption
A118: 45671 | B118: Quetta | C118: Assault | D118: Dr Bahar Shah, Dr Hafeez Mandokhail | E118: Protest against arrest of leaders | F118: Attacking and assaulting Director General Health | G118: 0 | H118: 0 | I118: Arrests made | J118: Dr Ameen Mandokhail, Director General Health Balochistan | K118: Doctors in Quetta are on strike protesting the arrest of their leaders, who were charged with assaulting the Director General of Health. The health department has directed disciplinary action against the striking doctors. | L118: Dawn News | M118: https://www.dawn.com/news/1885044 | N118: English | O118: Quetta | P118: Assault / Firing
A119: 45672 | B119: Karachi | C119: Insurrection | D119: President Yoon Suk Yeol | E119: Power grab | F119: Failed martial law declaration | G119: 0 | H119: 0 | I119: Attempt to arrest | K119: President Yoon Suk Yeol faces impeachment and insurrection charges after attempting to impose martial law in South Korea. His refusal to attend the trial has led to procedural adjournments, while investigators prepare a new arrest attempt. | L119: Dawn News | M119: https://www.dawn.com/news/1885230 | N119: English | O119: Karachi | P119: Police Action / Arrests
A120: 45673 | B120: Karachi | C120: Fraud | D120: Mohsin, Tanveer | E120: Financial gain | F120: Misuse of Kisan Card | G120: 0 | H120: 0 | I120: Employees expelled, stolen amounts recovered | J120: Ali Sher, Muhammad Bashir | K120: Two bank employees were fired for fraudulently withdrawing cash from Kisan Card accounts. The fraud was uncovered when beneficiaries received unauthorized SMS alerts about deductions. | L120: Dawn News | M120: https://www.dawn.com/news/1885590 | N120: English | O120: Karachi | P120: Fraud / Corruption
A121: 45685 | B121: Multan | C121: Explosion | D121: 8 nominated and 7 unidentified persons, 3 arrested | E121: Negligence in safety procedures | F121: Gas tanker explosion | G121: 6 | H121: 38 | I121: Case registered, 3 arrested, inquiry committee formed | K121: A gas tanker explosion in Multan resulted in 6 deaths and 38 injuries, with significant property damage. Police have registered a case and arrested 3 individuals. | L121: Dawn News | M121: https://www.dawn.com/news/1888198 | N121: English | O121: Multan | P121: Terrorism
A122: 45677 | B122: Muzaffargarh | C122: Accident | F122: Motorcycle collision | G122: 1 | H122: 1 | I122: Rescue staff provided first aid and shifted the injured to hospital | J122: Asia Bibi, 20F, deceased; Faqeer Muhammad, injured | K122: One person was killed and another seriously injured in a motorcycle accident at Chowk Qureshi near Sohrani Bypass. The deceased was identified as Asia Bibi, 20. | L122: Dawn News | M122: https://www.dawn.com/news/1886359 | N122: English | O122: Muzaffargarh | P122: Accident / Hit & Run
A123: 45673 | B123: Lahore | C123: Cybercrime | D123: Shahbaz Gill, Imran Riaz Khan, Muhammad Nadeem Javed, Muhammad Ejaz, Aamir Abbas | E123: To deteriorate the good relation of Pakistan with international powers | F123: Editing and spreading doctored images/videos | G123: 0 | H123: 0 | I123: FIR registered, suspects arrested | K123: The FIA has registered a case against PTI leader Shahbaz Gill and YouTuber Imran Riaz Khan for allegedly spreading doctored images/videos of public figures, leading to their arrest along with two others. | L123: Dawn News | M123: https://www.dawn.com/news/1885601 | N123: English | O123: Lahore | P123: Cybercrime
A124: 45663 | B124: Karachi | C124: Human Smuggling | D124: Raheemullah and Abdur Rehman | E124: Financial gain | F124: Illegal migration facilitation | G124: 0 | H124: 0 | I124: Two Afghans arrested, raids conducted | J124: Pakistani migrants | K124: The Federal Investigation Agency arrested two Afghan agents involved in human smuggling linked to a capsized boat incident in Greece. Evidence of their operations and contacts with victims was recovered. | L124: Dawn News | M124: https://www.dawn.com/news/1883306 | N124: English | O124: Karachi | P124: Human Trafficking
A125: 45672 | B125: Lahore | C125: Vandalism | D125: 32 people including PTI leaders Dr Yasmin Rashid, Mian Mehmoodur Rasheed, Senator Ejaz Chaudhry | E125: Political protest | F125: Setting fire to the PML-N office | G125: 0 | H125: 0 | I125: Indictment by Anti-Terrorism Court | J125: PML-N office in Model Town | K125: A Lahore Anti-Terrorism Court indicted 32 individuals, including prominent PTI leaders, for allegedly setting fire to the PML-N office during protests on May 9, 2023. | L125: Dawn News | M125: https://www.dawn.com/news/1885379 | N125: English | O125: Lahore | P125: Terrorism
A126: 45674 | B126: Faisalabad | C126: Gang Rape | D126: 2 unidentified men | E126: Job promise | F126: Gang-rape | G126: 0 | H126: 0 | I126: FIR registered | J126: Unnamed female, divorcee | K126: Two men were booked by Faisalabad police for gang-raping a woman who was promised a job. | L126: Dawn News | M126: https://www.dawn.com/news/1885731/call-to-introduce-industrial-hemp-as-cash-crop-to-rescue-textile-industry | N126: English | O126: Faisalabad | P126: Rape / Sexual Assault
A127: 45663 | B127: Mansehra | C127: Corruption | D127: Aftabul Islam Shah, Gohar Ishaq, Assad Jamal, Mohammad Rafique | E127: Financial gain | F127: Embezzlement in development schemes | G127: 0 | H127: 0 | I127: FIR registered, 2 arrested, 3 secured pre-arrest bail | J127: Not specified | K127: The Khyber Pakhtunkhwa Anti-Corruption Establishment has booked four officials for large-scale financial corruption and embezzlement in development schemes, with one suspect arrested and an FIR lodged against them. | L127: Dawn News | M127: https://www.dawn.com/news/1883303 | N127: English | O127: Mansehra | P127: Fraud / Corruption
A128: 45683 | B128: Faisalabad | C128: Gang Rape | D128: 4 unidentified men | E128: Not specified | F128: Kidnapping and gang-rape | G128: 0 | H128: 1 | I128: All four suspects arrested | J128: 18-year-old girl | K128: An 18-year-old girl was allegedly gang-raped by four men in D-Type Colony, Faisalabad after being kidnapped while purchasing medicine. Police have arrested all suspects. | L128: Dawn News | M128: https://www.dawn.com/news/1887698 | N128: English | O128: Faisalabad | P128: Rape / Sexual Assault
A129: 45681 | B129: Sialkot | C129: Human Trafficking | D129: Irfan Yousaf | E129: Financial gain | F129: Using an Umrah visa to facilitate illegal travel | G129: 0 | H129: 0 | I129: Both arrested and sent to FIA anti-human trafficking cell | J129: Saqlain Abbas, resident of Sialkot | K129: Seventeen passengers were offloaded from flights at Sialkot International Airport, and an illegal immigrant was detained after attempting to travel to Greece. The agent facilitating the illegal travel was also arrested. | L129: Dawn News | M129: https://www.dawn.com/news/1887348 | N129: English | O129: Sialkot | P129: Human Trafficking
A130: 45684 | B130: Gujrat | C130: Human Trafficking | D130: Muhammad Ijaz | E130: Financial gain | F130: Sending immigrants on false visas | G130: 0 | H130: 0 | I130: 13 cases lodged, 5 human traffickers arrested, passports blocked, bank accounts seized | J130: Muhammad Tayyab, Muhammad Arif | K130: Two Pakistani immigrants returned from Senegal after being victims of human trafficking. Their agent charged them exorbitantly for a trip to Spain but sent them to Senegal instead. | L130: Dawn News | M130: https://www.dawn.com/news/1887884/more-illegal-immigrants-return | N130: English | O130: Gujrat | P130: Human Trafficking
A131: 45686 | B131: Karachi | C131: Exploitation of a disabled person | D131: Lucrecia Kormassa Koiyan | E131: Personal gain | F131: Twerking on a disabled person | G131: 0 | H131: 0 | I131: Investigation launched, Arrested | J131: Disabled man | K131: A healthcare worker in Georgia has been charged with exploitation of a disabled person after a viral TikTok video showed her twerking on the head of a disabled individual. The police are investigating the incident further. | L131: Express Tribune | M131: https://tribune.com.pk/story/2525224/19-year-old-georgia-healthcare-worker-faces-felony-for-twerking-on-disabled-persons-head | N131: English | O131: Karachi | P131: Other
A132: 45671 | B132: Karachi | C132: Terrorism | D132: Khorij faction | E132: Terrorism | F132: Intelligence-based operation | G132: 27 | H132: 0 | I132: Ongoing operations | J132: 27 terrorists killed | K132: In an intelligence-based operation in Balochistan, 27 terrorists from the Khorij faction were killed as part of ongoing operations led by the Army Chief. | L132: Express Tribune | M132: https://tribune.com.pk/story/2522077/economy-severely-damaged-under-ptis-leadership-pm-shahbaz-sharif | N132: English | O132: Karachi | P132: Terrorism
A133: 45682 | B133: Karachi | C133: Harassment | D133: Sindh police, officials of Sukhan police station | E133: Unjustified restrictions and harassment | F133: Unlawful detainments, demanding bribes, restricting movement | G133: 0 | H133: 0 | I133: Notices issued by Sindh High Court | J133: Six Chinese nationals including Mr Xu Hui and Ms Deng Huan | K133: A petition filed by six Chinese nationals in the Sindh High Court alleges harassment and unlawful restrictions by Sindh police, including demands for bribes and unjustified detainments, impacting their ability to conduct business. | L133: Dawn News | M133: https://www.dawn.com/news/1887503 | N133: English | O133: Karachi | P133: Rape / Sexual Assault
A134: 45658 | B134: Karachi | C134: Violence against health workers | D134: Local family | E134: Refusal of vaccination | F134: Attack on polio vaccination team | G134: 0 | H134: 3 | I134: Investigation ongoing | J134: 3 health workers | K134: In December 2024, a polio vaccination team in Karachi's Korangi district was attacked by a local family when they insisted on administering the vaccine, resulting in injuries to three health workers. | L134: Dawn News | M134: https://www.dawn.com/news/1882454 | N134: English | O134: Karachi | P134: Assault / Firing
A135: 45667 | B135: Chaman | C135: Terrorism | D135: Baloch Liberation Army, Majeed Brigade | E135: Terrorism | F135: Blast from an improvised explosive device (IED) | G135: 0 | H135: 3 | I135: Investigation ongoing, culprits to be brought to justice | J135: 3 civilians, 2 with minor injuries, 1 hospitalized | K135: Three civilians were injured in a blast from an IED targeting a truck carrying Frontier Corps personnel in Chaman, Balochistan. The attack was condemned by government officials, and the Baloch Liberation Army claimed responsibility. | L135: Dawn News | M135: https://www.dawn.com/news/1884325 | N135: English | O135: Chaman | P135: Terrorism
... A138: 45687 | B138: Karachi | C138: DUI | D138: Emily Hernandez | E138: Recklessness | F138: Driving on the wrong side of the highway | G138: 1 | H138: 1 | I138: Sentenced to 10 years in prison | J138: Victoria Wilson, 32 | K138: Emily Hernandez was sentenced to 10 years in prison for causing a deadly drunk driving crash that resulted in the death of Victoria Wilson. Hernandez was driving on the wrong side of the highway with a blood-alcohol content of .20%. | L138: Express Tribune | M138: https://tribune.com.pk/story/2525534/january-6-rioter-emily-hernandez-sentenced-to-10-years-for-fatal-dui-crash | N138: English | O138: Karachi | P138: Custody / Jail
A139: 45662 | B139: Karachi | C139: Terrorism | D139: Tehr��eek-i-Taliban Pakistan (TTP), Balochistan Liberation Army (BLA) | E139: Religiously motivated militancy, nationalist insurgency | F139: Terrorist attacks, coordinated gun-and-bomb attacks, suicide bombers | G139: Not specified | H139: Not specified | I139: Cross-border airstrike in Afghanistan | J139: Security forces, non-Baloch workers, miners, Chinese nationals | K139: In 2024, Pakistan experienced a significant increase in terrorist violence, primarily attributed to the TTP and BLA, with multiple high-profile attacks targeting security forces and civilians, particularly in Karachi. | L139: Dawn News | M139: https://www.dawn.com/news/1883212 | N139: English | O139: Karachi | P139: Terrorism
A140: 45685 | B140: Karachi | C140: Corruption | D140: 11 companies, Star Business Solution, Moonlight, two brothers | E140: Financial gain | F140: Fraudulent solar panel imports, money laundering | G140: 0 | H140: 0 | I140: Investigation initiated, STR filed, PCA findings revealed | J140: Not specified | K140: A Senate subcommittee is investigating a multi-billion-rupee corruption scandal involving 11 companies in fraudulent solar panel imports, with allegations of money laundering and inflated prices. | L140: Express Tribune | M140: https://tribune.com.pk/story/2524965/senate-body-probes-corruption-in-solar-panel-import-scandal | N140: English | O140: Karachi | P140: Fraud / Corruption
A141: 45675 | B141: Daska | C141: Land Grabbing | D141: Daska local administration, Assistant Commissioner Maham Mushtaq | E141: Targeting the Ahmadi community | F141: Demolition of worship place | G141: 0 | H141: 0 | I141: Demolition carried out by local administration with police presence | J141: Ahmadiyya community, worship place built by Zafarullah Khan | K141: The local administration in Daska demolished a historical worship place built by Zafarullah Khan, claiming it was an encroachment. The action has been criticized as part of a broader pattern of targeting the Ahmadi community. | L141: Dawn News | M141: https://www.dawn.com/news/1886020 | N141: English | O141: Daska | P141: Land Grabbing / Dispute
A142: 45674 | B142: Karachi | C142: Corruption | D142: Imran Khan, Bushra Bibi | E142: Financial gain | F142: Embezzlement | G142: 0 | H142: 0 | I142: Conviction, Sentences announced | J142: Pakistani public | K142: Former Prime Minister Imran Khan and his wife Bushra Bibi were convicted in a ��190 million corruption case, receiving prison sentences of 14 and 7 years respectively, along with fines. The court ordered the forfeiture of the Al-Qadir University Project Trust property to the Federal Government. | L142: Express Tribune | M142: https://tribune.com.pk/story/2522753/govt-defends-merit-based-verdict-in-190-million-case | N142: English | O142: Karachi | P142: Fraud / Corruption
A143: 45670 | B143: Karachi | C143: Corruption | D143: Imran Khan, Bushra Bibi | E143: Personal gain | F143: Financial transactions through charitable organisations | G143: 0 | H143: 0 | I143: NAB arrested Imran Khan | K143: Punjab Information Minister Azma Bukhari criticized PTI leaders for failing to appear in court regarding corruption charges. Imran Khan and his wife, Bushra Bibi, are accused of financial misconduct involving ��190 million. | L143: Express Tribune | M143: https://tribune.com.pk/story/2521821/punjab-information-minister-criticises-pti-leaders-for-avoiding-court | N143: English | O143: Karachi | P143: Fraud / Corruption
A144: 45670 | B144: Kacchi District | C144: Terrorism | D144: 27 terrorists | E144: Destabilising efforts | F144: Intelligence-based operation | G144: 27 | H144: 0 | I144: Operation conducted, terrorists neutralised | J144: Security forces and civilians affected by previous attacks | K144: Security forces conducted an intelligence-based operation in Kacchi District, resulting in the elimination of 27 terrorists responsible for multiple attacks on security forces and civilians. | L144: Express Tribune | M144: https://tribune.com.pk/story/2521873/security-forces-eliminate-27-terrorists-in-balochistan-operation-ispr | N144: English | O144: Kacchi District | P144: Terrorism
A145: 45663 | B145: Kurram | C145: Terrorism | D145: unknown assailants, 25 to 30 terrorists | E145: sabotage a nascent peace deal | F145: open fire on convoy | G145: 0 | H145: 7 | I145: FIR registered, 2 suspects arrested | J145: Javedullah Mehsud, Deputy Commissioner, injured | K145: A convoy carrying Kurram Deputy Commissioner Javedullah Mehsud was attacked by armed men, injuring seven people. An FIR was lodged under terrorism charges against unknown assailants. | L145: Express Tribune | M145: https://tribune.com.pk/story/2520302/k-p-resorts-to-stringent-measures-to-save-kurram-deal | N145: English | O145: Kurram | P145: Terrorism
A146: 45671 | B146: Islamabad | C146: Murder, Terrorism | D146: Imran Khan, Bushra Bibi, Ali Amin Gandapur, Omar Ayub Khan, Sheikh Waqas Akram, Salman Akram Raja, Murad Saeed, Zulfi Bukhari, Hammad Azhar, Raoof Hassan | E146: To get Imran Khan released from jail | F146: Hit-and-run incident | G146: 4 | H146: 0 | I146: FIR registered, interim bail granted | K146: Bushra Bibi appeared in court regarding the death of four Rangers personnel in a hit-and-run incident during PTI protests. An FIR has been registered against several PTI leaders, including Imran Khan. | L146: Dawn News | M146: https://www.dawn.com/news/1885131 | N146: English | O146: Islamabad | P146: Terrorism
A147: 45661 | B147: Peshawar | C147: Shooting | D147: Armed assailants | E147: Ongoing feud between rival families | F147: Ambush with gunfire | G147: 6 | H147: 6 | I147: Investigation initiated, formal case expected | J147: Islam Allah, Muhammad Tariq, Kamran Ilahi, Yusuf, Abbas, Ali Hassan | K147: A shooting incident in Peshawar's Machni Gate area resulted in six deaths and six injuries when armed assailants ambushed a wedding convoy. The attack was linked to an ongoing feud between rival families. | L147: Express Tribune | M147: https://tribune.com.pk/story/2520040/shooting-on-wedding-car-leaves-six-dead-in-peshawar | N147: English | O147: Peshawar | P147: Assault / Firing
A148: 45684 | B148: Karachi | C148: Kidnapping | D148: 40 notorious dacoits | E148: Rivalry between tribes | F148: Kidnapping | G148: 12 | H148: 0 | I148: Bounties announced, joint operation conducted | J148: At least 8 people kidnapped from rival tribe | K148: The Punjab government has announced bounties on 40 notorious dacoits involved in organized crime, following a series of kidnappings and a recent rocket attack that killed 12 policemen. | L148: Express Tribune | M148: https://tribune.com.pk/story/2524713/bounties-set-on-40-katcha-bandits | N148: English | O148: Karachi | P148: Kidnapping
A149: 45665 | B149: Karachi | C149: Corruption | D149: Chaudhry Parvez Elahi, Moonis Elahi, Muhammad Khan Bhatti | E149: Financial gain | F149: Receiving kickbacks in developmental projects | G149: 0 | H149: 0 | I149: Indicted in NAB corruption case | K149: Former Punjab chief minister Chaudhry Parvez Elahi has been indicted in a NAB corruption case involving Rs1.23 billion for receiving kickbacks in developmental projects. His son Moonis Elahi's assets were frozen, and he was declared a proclaimed offender. | L149: Express Tribune | M149: https://tribune.com.pk/story/2520713/parvez-elahi-indicted-in-nab-corruption-case | N149: English | O149: Karachi | P149: Fraud / Corruption
A150: 45671 | B150: Karachi | C150: Sexual Assault | D150: Neil Gaiman | E150: Power dynamics, consent issues | F150: Non-consensual acts under the guise of BDSM, sexual misconduct | G150: 0 | H150: 0 | J150: Scarlett Pavlovich, Caroline | K150: Neil Gaiman faces multiple allegations of sexual assault from several women, including claims of non-consensual acts and misconduct. The accusations have led to significant repercussions in his career. | L150: Express Tribune | M150: https://tribune.com.pk/story/2521886/neil-gaiman-faces-sexual-assault-allegations-in-new-york-magazine-cover-story | N150: English | O150: Karachi | P150: Rape / Sexual Assault
A151: 45688 | B151: Karachi | C151: Sexual Harassment | D151: Justin Baldoni | E151: Inappropriate behavior during filming | F151: Improvising unwanted kissing and making inappropriate comments | G151: 0 | H151: 0 | I151: Lawsuit filed | J151: Blake Lively, actress | K151: Blake Lively has filed a lawsuit against her co-star Justin Baldoni, alleging sexual harassment and a hostile work environment during the filming of the adaptation of 'It Ends with Us'. Baldoni has countered with a defamation lawsuit. | L151: Express Tribune | M151: https://tribune.com.pk/article/97912/booktok-is-finally-waking-up-from-the-colleen-hoover-fever-dream | N151: English | O151: Karachi | P151: Rape / Sexual Assault
A152: 45671 | B152: Karachi | C152: Sexual Assault | D152: Neil Gaiman | E152: Sexual control | F152: Sexual assault | G152: 0 | H152: 0 | I152: Not mentioned | J152: Multiple women, including Scarlett Pavlovich and Katherine Kendall | K152: J.K. Rowling criticized the silence surrounding Neil Gaiman, who has been accused of sexual assault by multiple women, comparing the situation to the #MeToo movement. | L152: Express Tribune | M152: https://tribune.com.pk/story/2522004/jk-rowling-likens-neil-gaiman-to-harvey-weinstein-condemns-literary-circle-for-silence | N152: English | O152: Karachi | P152: Rape / Sexual Assault
A153: 45686 | B153: Karachi | C153: Sexual Harassment | D153: Justin Baldoni | E153: Uncomfortable work environment | F153: Sexually suggestive remarks, increasing intimate scenes, showing explicit videos | G153: 0 | H153: 0 | I153: Lawsuit filed | J153: Blake Lively, 37F, actress | K153: Blake Lively has accused director Justin Baldoni of sexual harassment during the filming of 'It Ends With Us', alleging inappropriate behavior and an uncomfortable work environment. | L153: Express Tribune | M153: https://tribune.com.pk/story/2525273/blake-livelys-flirty-texts-with-justin-baldoni-while-filming-it-ends-with-us-exposed | N153: English | O153: Karachi | P153: Rape / Sexual Assault
A154: 45660 | B154: Karachi | C154: Domestic Violence | D154: Majid Bashir, police inspector | F154: Domestic violence and life threats | G154: 0 | H154: 0 | I154: Case filed at Defence C police station | K154: Stage actor Nargis has forgiven her husband Majid Bashir, a police inspector, and wants to withdraw the charges of domestic violence against him, following a mutual settlement agreement. | L154: Dawn News | M154: https://images.dawn.com/news/1193111/nargis-reaches-rapprochement-with-husband-after-domestic-violence-charges | N154: English | O154: Karachi | P154: Domestic Violence
A155: 45688 | B155: Karachi | C155: Sexual Misconduct | D155: Russell Brand | E155: Power imbalance | F155: Inappropriate on-air comments, urinating in studio cups, throwing objects, sexual misconduct | G155: 0 | H155: 0 | I155: Metropolitan Police continues to investigate multiple reports of sexual offenses | J155: Unnamed staff members | K155: The BBC has apologized after an internal review revealed that staff felt unable to report concerns about Russell Brand's behavior, including allegations of sexual misconduct and inappropriate actions during his tenure. | L155: Express Tribune | M155: https://tribune.com.pk/story/2525587/bbc-apologizes-after-staff-felt-unable-to-raise-concerns-about-russell-brand | N155: English | O155: Karachi | P155: Rape / Sexual Assault
A156: 45682 | B156: Karachi | C156: Terrorism | D156: Baloch Liberation Army (BLA) | E156: Destabilise Pakistan | F156: Coercion for suicide bombings | G156: 0 | H156: 0 | J156: Adila Baloch, Shari Baloch, Mahil Baloch | K156: Najeebullah, a former commander of the Baloch Republican Army, surrendered to the government and revealed that militant organizations exploit women for terrorist activities, coercing them into suicide bombings. | L156: Express Tribune | M156: https://tribune.com.pk/story/2524363/bra-commander-surrenders-to-govt | N156: English | O156: Karachi | P156: Terrorism
A157: 45680 | B157: Karachi | C157: Harassment, Physical Assault | D157: Babar Azam | E157: Coercion, Broken marriage promises | F157: Physical assault, Coercing into abortion | G157: 0 | H157: 0 | I157: Case registration directed by lower court | J157: Hamiza Mukhtar | K157: Hamiza Mukhtar has accused cricketer Babar Azam of harassment and physical assault, claiming he coerced her into an abortion and broke marriage promises. The Lahore High Court has summoned her to appear for further proceedings. | L157: Pakistan Today | M157: https://www.pakistantoday.com.pk/2025/01/23/lhc-summons-complainant-in-babar-azam-case-warns-of-ruling-in-absence | N157: English | O157: Karachi | P157: Rape / Sexual Assault
A158: 45683 | B158: Karachi | C158: Sexual Assault | D158: Kobe Bryant | F158: Groping and choking | G158: 0 | H158: 1 | I158: Police interview conducted | J158: 19-year-old hotel employee | K158: A new documentary revisits the 2003 sexual assault allegations against Kobe Bryant, detailing the encounter and the subsequent legal proceedings. | L158: Express Tribune | M158: https://tribune.com.pk/story/2524628/new-kobe-bryant-documentary-revisits-2003-assault-allegations-questions-legacy | N158: English | O158: Karachi | P158: Rape / Sexual Assault
A159: 45680 | B159: Karachi | C159: Rape, Harassment, Blackmail, Financial Exploitation | D159: Babar Azam | F159: Blackmail, Fornication under the pretext of marriage | G159: 0 | H159: 0 | I159: FIR filed, Police unwilling to register complaint | J159: Unnamed woman | K159: A woman has accused former cricketer Babar Azam of rape, harassment, and blackmail, claiming he promised to marry her but later betrayed her. She filed an FIR but faced challenges with police unwillingness to register her complaint. | L159: Express Tribune | M159: https://tribune.com.pk/story/2524030/lhc-issues-new-order-in-babar-azams-alleged-sexual-assault-case | N159: English | O159: Karachi | P159: Rape / Sexual Assault
A160: 45666 | B160: Karachi | C160: Sexual Assault, Theft | D160: Stefon Diggs, Darez (Marsean) | E160: Financial gain, Personal vendetta | F160: Attempted sexual assault, Attempted robbery | G160: 0 | H160: 0 | I160: Allegations made, no police action reported | J160: Chris Blake Griffith | K160: Chris Blake Griffith accused Stefon Diggs of drugging and attempting to sexually assault him, and later attempted to rob his home. DJ Akademiks claimed that Griffith fabricated DMs with Drake to gain attention. | L160: Express Tribune | M160: https://tribune.com.pk/story/2521078/chris-blake-griffith-faked-drake-dms-after-rapper-refused-to-expose-stefon-diggs-dj-akademiks | N160: English | O160: Karachi | P160: Rape / Sexual Assault
A161: 45667 | B161: Khuzdar | C161: Terrorism | D161: BLA militants | E161: Separatism | F161: Brazen attack, pillaging, looting | G161: 0 | H161: 0 | I161: Delayed response of security forces | J161: Local Levies personnel taken hostage | K161: BLA militants attacked the Zehri area of Khuzdar district, destroying government buildings and looting a private bank. No casualties were reported, but the attack highlighted the state's unpreparedness. | L161: Dawn News | M161: https://www.dawn.com/news/1884214 | N161: English | O161: Khuzdar | P161: Terrorism
A162: 45659 | B162: Karachi | C162: Terrorism | D162: Tehreek-i-Taliban Pakistan (TTP) | E162: Political instability and insurgency | F162: Terrorist incidents | G162: 788 | H162: 0 | I162: Over 59,000 intelligence-based operations conducted | J162: Ordinary citizens, security forces personnel | K162: The report highlights a significant increase in terrorist incidents in Pakistan, particularly in Khyber Pakhtunkhwa, with a rise in casualties from 238 in 2021 to 788 in 2024, attributed to the activities of the Tehreek-i-Taliban Pakistan. | L162: Dawn News | M162: https://www.dawn.com/news/1882576 | N162: English | O162: Karachi | P162: Terrorism
...

Sheet Analysis
A1: Crime News Analysis
A2: Total news (clean) | B2: =COUNTA(Data!$N$2:$N$20512) -> 20511 | C2: Repeat reports removed | D2: 436
A3: Exact duplicates removed | B3: 138
A4: News before duplicate removal | B4: =B2+B3+D2 -> 21085
A5: 1. News by Language
A6: Language | B6: News | C6: % of total
A7: Urdu | B7: =COUNTIF(Data!$N$2:$N$20512,A7) -> 15816 | C7: =B7/$B$2 -> 0.77109843
A8: English | B8: =COUNTIF(Data!$N$2:$N$20512,A8) -> 4695 | C8: =B8/$B$2 -> 0.22890157
A9: Total | B9: =SUM(B7:B8) -> 20511 | C9: =SUM(C7:C8) -> 1
A12: 2. Top 25 Cities by Number of News
A13: Rank | B13: City | C13: Total News | D13: Urdu | E13: English | F13: % of total
A14: 1 | B14: Lahore | C14: =COUNTIF(Data!$O$2:$O$20512,B14) -> 4038 | D14: =COUNTIFS(Data!$O$2:$O$20512,B14,Data!$N$2:$N$20512,"Urdu") -> 3510 | E14: =COUNTIFS(Data!$O$2:$O$20512,B14,Data!$N$2:$N$20512,"English") -> 528 | F14: =C14/$B$2 -> 0.19686997
A15: 2 | B15: Faisalabad | C15: =COUNTIF(Data!$O$2:$O$20512,B15) -> 2462 | D15: =COUNTIFS(Data!$O$2:$O$20512,B15,Data!$N$2:$N$20512,"Urdu") -> 2368 | E15: =COUNTIFS(Data!$O$2:$O$20512,B15,Data!$N$2:$N$20512,"English") -> 94 | F15: =C15/$B$2 -> 0.12003315
A16: 3 | B16: Karachi | C16: =COUNTIF(Data!$O$2:$O$20512,B16) -> 2376 | D16: =COUNTIFS(Data!$O$2:$O$20512,B16,Data!$N$2:$N$20512,"Urdu") -> 1427 | E16: =COUNTIFS(Data!$O$2:$O$20512,B16,Data!$N$2:$N$20512,"English") -> 949 | F16: =C16/$B$2 -> 0.11584028
A17: 4 | B17: Islamabad | C17: =COUNTIF(Data!$O$2:$O$20512,B17) -> 981 | D17: =COUNTIFS(Data!$O$2:$O$20512,B17,Data!$N$2:$N$20512,"Urdu") -> 555 | E17: =COUNTIFS(Data!$O$2:$O$20512,B17,Data!$N$2:$N$20512,"English") -> 426 | F17: =C17/$B$2 -> 0.047827995
A18: 5 | B18: Kasur | C18: =COUNTIF(Data!$O$2:$O$20512,B18) -> 871 | D18: =COUNTIFS(Data!$O$2:$O$20512,B18,Data!$N$2:$N$20512,"Urdu") -> 852 | E18: =COUNTIFS(Data!$O$2:$O$20512,B18,Data!$N$2:$N$20512,"English") -> 19 | F18: =C18/$B$2 -> 0.042465019
A19: 6 | B19: Kamoke | C19: =COUNTIF(Data!$O$2:$O$20512,B19) -> 609 | D19: =COUNTIFS(Data!$O$2:$O$20512,B19,Data!$N$2:$N$20512,"Urdu") -> 607 | E19: =COUNTIFS(Data!$O$2:$O$20512,B19,Data!$N$2:$N$20512,"English") -> 2 | F19: =C19/$B$2 -> 0.029691385
A20: 7 | B20: Rawalpindi | C20: =COUNTIF(Data!$O$2:$O$20512,B20) -> 533 | D20: =COUNTIFS(Data!$O$2:$O$20512,B20,Data!$N$2:$N$20512,"Urdu") -> 313 | E20: =COUNTIFS(Data!$O$2:$O$20512,B20,Data!$N$2:$N$20512,"English") -> 220 | F20: =C20/$B$2 -> 0.025986056
A21: 8 | B21: Ferozewala | C21: =COUNTIF(Data!$O$2:$O$20512,B21) -> 488 | D21: =COUNTIFS(Data!$O$2:$O$20512,B21,Data!$N$2:$N$20512,"Urdu") -> 488 | E21: =COUNTIFS(Data!$O$2:$O$20512,B21,Data!$N$2:$N$20512,"English") -> 0 | F21: =C21/$B$2 -> 0.023792112
A22: 9 | B22: Peshawar | C22: =COUNTIF(Data!$O$2:$O$20512,B22) -> 324 | D22: =COUNTIFS(Data!$O$2:$O$20512,B22,Data!$N$2:$N$20512,"Urdu") -> 192 | E22: =COUNTIFS(Data!$O$2:$O$20512,B22,Data!$N$2:$N$20512,"English") -> 132 | F22: =C22/$B$2 -> 0.015796402
A23: 10 | B23: Gujranwala | C23: =COUNTIF(Data!$O$2:$O$20512,B23) -> 314 | D23: =COUNTIFS(Data!$O$2:$O$20512,B23,Data!$N$2:$N$20512,"Urdu") -> 285 | E23: =COUNTIFS(Data!$O$2:$O$20512,B23,Data!$N$2:$N$20512,"English") -> 29 | F23: =C23/$B$2 -> 0.015308859
A24: 11 | B24: Quetta | C24: =COUNTIF(Data!$O$2:$O$20512,B24) -> 270 | D24: =COUNTIFS(Data!$O$2:$O$20512,B24,Data!$N$2:$N$20512,"Urdu") -> 122 | E24: =COUNTIFS(Data!$O$2:$O$20512,B24,Data!$N$2:$N$20512,"English") -> 148 | F24: =C24/$B$2 -> 0.013163668
A25: 12 | B25: Sialkot | C25: =COUNTIF(Data!$O$2:$O$20512,B25) -> 213 | D25: =COUNTIFS(Data!$O$2:$O$20512,B25,Data!$N$2:$N$20512,"Urdu") -> 179 | E25: =COUNTIFS(Data!$O$2:$O$20512,B25,Data!$N$2:$N$20512,"English") -> 34 | F25: =C25/$B$2 -> 0.010384672
... A38: 25 | B38: Gujrat | C38: =COUNTIF(Data!$O$2:$O$20512,B38) -> 89 | D38: =COUNTIFS(Data!$O$2:$O$20512,B38,Data!$N$2:$N$20512,"Urdu") -> 49 | E38: =COUNTIFS(Data!$O$2:$O$20512,B38,Data!$N$2:$N$20512,"English") -> 40 | F38: =C38/$B$2 -> 0.0043391351
B39: City Not Specified | C39: =COUNTIF(Data!$O$2:$O$20512,"Not Specified") -> 548
B40: Total Unique Cities / Areas | C40: 952
A43: 3. News by Crime Category
A44: Rank | B44: Crime Category | C44: Total News | D44: Urdu | E44: English | F44: % of total
A45: 1 | B45: Murder | C45: =COUNTIF(Data!$P$2:$P$20512,B45) -> 2876 | D45: =COUNTIFS(Data!$P$2:$P$20512,B45,Data!$N$2:$N$20512,"Urdu") -> 2150 | E45: =COUNTIFS(Data!$P$2:$P$20512,B45,Data!$N$2:$N$20512,"English") -> 726 | F45: =C45/$B$2 -> 0.14021744
A46: 2 | B46: Fraud / Corruption | C46: =COUNTIF(Data!$P$2:$P$20512,B46) -> 2747 | D46: =COUNTIFS(Data!$P$2:$P$20512,B46,Data!$N$2:$N$20512,"Urdu") -> 2358 | E46: =COUNTIFS(Data!$P$2:$P$20512,B46,Data!$N$2:$N$20512,"English") -> 389 | F46: =C46/$B$2 -> 0.13392814
A47: 3 | B47: Accident / Hit & Run | C47: =COUNTIF(Data!$P$2:$P$20512,B47) -> 1923 | D47: =COUNTIFS(Data!$P$2:$P$20512,B47,Data!$N$2:$N$20512,"Urdu") -> 1748 | E47: =COUNTIFS(Data!$P$2:$P$20512,B47,Data!$N$2:$N$20512,"English") -> 175 | F47: =C47/$B$2 -> 0.093754571
A48: 4 | B48: Terrorism | C48: =COUNTIF(Data!$P$2:$P$20512,B48) -> 1822 | D48: =COUNTIFS(Data!$P$2:$P$20512,B48,Data!$N$2:$N$20512,"Urdu") -> 692 | E48: =COUNTIFS(Data!$P$2:$P$20512,B48,Data!$N$2:$N$20512,"English") -> 1130 | F48: =C48/$B$2 -> 0.088830384
A49: 5 | B49: Rape / Sexual Assault | C49: =COUNTIF(Data!$P$2:$P$20512,B49) -> 1256 | D49: =COUNTIFS(Data!$P$2:$P$20512,B49,Data!$N$2:$N$20512,"Urdu") -> 1055 | E49: =COUNTIFS(Data!$P$2:$P$20512,B49,Data!$N$2:$N$20512,"English") -> 201 | F49: =C49/$B$2 -> 0.061235435
A50: 6 | B50: Drugs | C50: =COUNTIF(Data!$P$2:$P$20512,B50) -> 1184 | D50: =COUNTIFS(Data!$P$2:$P$20512,B50,Data!$N$2:$N$20512,"Urdu") -> 1045 | E50: =COUNTIFS(Data!$P$2:$P$20512,B50,Data!$N$2:$N$20512,"English") -> 139 | F50: =C50/$B$2 -> 0.057725123
A51: 7 | B51: Robbery / Theft | C51: =COUNTIF(Data!$P$2:$P$20512,B51) -> 1179 | D51: =COUNTIFS(Data!$P$2:$P$20512,B51,Data!$N$2:$N$20512,"Urdu") -> 948 | E51: =COUNTIFS(Data!$P$2:$P$20512,B51,Data!$N$2:$N$20512,"English") -> 231 | F51: =C51/$B$2 -> 0.057481351
A52: 8 | B52: Kidnapping | C52: =COUNTIF(Data!$P$2:$P$20512,B52) -> 1168 | D52: =COUNTIFS(Data!$P$2:$P$20512,B52,Data!$N$2:$N$20512,"Urdu") -> 978 | E52: =COUNTIFS(Data!$P$2:$P$20512,B52,Data!$N$2:$N$20512,"English") -> 190 | F52: =C52/$B$2 -> 0.056945054
A53: 9 | B53: Mob / Sectarian Violence | C53: =COUNTIF(Data!$P$2:$P$20512,B53) -> 709 | D53: =COUNTIFS(Data!$P$2:$P$20512,B53,Data!$N$2:$N$20512,"Urdu") -> 527 | E53: =COUNTIFS(Data!$P$2:$P$20512,B53,Data!$N$2:$N$20512,"English") -> 182 | F53: =C53/$B$2 -> 0.034566818
A54: 10 | B54: Illegal Weapons | C54: =COUNTIF(Data!$P$2:$P$20512,B54) -> 632 | D54: =COUNTIFS(Data!$P$2:$P$20512,B54,Data!$N$2:$N$20512,"Urdu") -> 610 | E54: =COUNTIFS(Data!$P$2:$P$20512,B54,Data!$N$2:$N$20512,"English") -> 22 | F54: =C54/$B$2 -> 0.030812735
A55: 11 | B55: Honor Killing | C55: =COUNTIF(Data!$P$2:$P$20512,B55) -> 598 | D55: =COUNTIFS(Data!$P$2:$P$20512,B55,Data!$N$2:$N$20512,"Urdu") -> 511 | E55: =COUNTIFS(Data!$P$2:$P$20512,B55,Data!$N$2:$N$20512,"English") -> 87 | F55: =C55/$B$2 -> 0.029155088
A56: 12 | B56: Cybercrime | C56: =COUNTIF(Data!$P$2:$P$20512,B56) -> 530 | D56: =COUNTIFS(Data!$P$2:$P$20512,B56,Data!$N$2:$N$20512,"Urdu") -> 383 | E56: =COUNTIFS(Data!$P$2:$P$20512,B56,Data!$N$2:$N$20512,"English") -> 147 | F56: =C56/$B$2 -> 0.025839793
... A81: 37 | B81: Environmental Violation | C81: =COUNTIF(Data!$P$2:$P$20512,B81) -> 23 | D81: =COUNTIFS(Data!$P$2:$P$20512,B81,Data!$N$2:$N$20512,"Urdu") -> 15 | E81: =COUNTIFS(Data!$P$2:$P$20512,B81,Data!$N$2:$N$20512,"English") -> 8 | F81: =C81/$B$2 -> 0.0011213495
B82: Total | C82: =SUM(C45:C81) -> 20511 | D82: =SUM(D45:D81) -> 15816 | E82: =SUM(E45:E81) -> 4695 | F82: =SUM(F45:F81) -> 1
A85: 4. Most Common Crime in Top 10 Cities
A86: City | B86: Top Crime Category | C86: News | D86: City Total
A87: Lahore | B87: Murder | C87: =COUNTIFS(Data!$O$2:$O$20512,A87,Data!$P$2:$P$20512,B87) -> 542 | D87: =COUNTIF(Data!$O$2:$O$20512,A87) -> 4038
A88: Karachi | B88: Murder | C88: =COUNTIFS(Data!$O$2:$O$20512,A88,Data!$P$2:$P$20512,B88) -> 469 | D88: =COUNTIF(Data!$O$2:$O$20512,A88) -> 2376
A89: Faisalabad | B89: Fraud / Corruption | C89: =COUNTIFS(Data!$O$2:$O$20512,A89,Data!$P$2:$P$20512,B89) -> 667 | D89: =COUNTIF(Data!$O$2:$O$20512,A89) -> 2462
A90: Islamabad | B90: Murder | C90: =COUNTIFS(Data!$O$2:$O$20512,A90,Data!$P$2:$P$20512,B90) -> 139 | D90: =COUNTIF(Data!$O$2:$O$20512,A90) -> 981
A91: Kasur | B91: Accident / Hit & Run | C91: =COUNTIFS(Data!$O$2:$O$20512,A91,Data!$P$2:$P$20512,B91) -> 159 | D91: =COUNTIF(Data!$O$2:$O$20512,A91) -> 871
A92: Kamoke | B92: Robbery / Theft | C92: =COUNTIFS(Data!$O$2:$O$20512,A92,Data!$P$2:$P$20512,B92) -> 128 | D92: =COUNTIF(Data!$O$2:$O$20512,A92) -> 609
A93: Rawalpindi | B93: Murder | C93: =COUNTIFS(Data!$O$2:$O$20512,A93,Data!$P$2:$P$20512,B93) -> 99 | D93: =COUNTIF(Data!$O$2:$O$20512,A93) -> 533
A94: Ferozewala | B94: Accident / Hit & Run | C94: =COUNTIFS(Data!$O$2:$O$20512,A94,Data!$P$2:$P$20512,B94) -> 160 | D94: =COUNTIF(Data!$O$2:$O$20512,A94) -> 488
A95: Peshawar | B95: Terrorism | C95: =COUNTIFS(Data!$O$2:$O$20512,A95,Data!$P$2:$P$20512,B95) -> 89 | D95: =COUNTIF(Data!$O$2:$O$20512,A95) -> 324
A96: Gujranwala | B96: Murder | C96: =COUNTIFS(Data!$O$2:$O$20512,A96,Data!$P$2:$P$20512,B96) -> 55 | D96: =COUNTIF(Data!$O$2:$O$20512,A96) -> 314
A99: 5. News by Newspaper / Source
A100: Rank | B100: Source | C100: Total News | D100: Urdu | E100: English | F100: % of total
A101: 1 | B101: Dunya News | C101: =COUNTIF(Data!$L$2:$L$20512,B101) -> 5017 | D101: =COUNTIFS(Data!$L$2:$L$20512,B101,Data!$N$2:$N$20512,"Urdu") -> 5017 | E101: =COUNTIFS(Data!$L$2:$L$20512,B101,Data!$N$2:$N$20512,"English") -> 0 | F101: =C101/$B$2 -> 0.24460046
A102: 2 | B102: Nawaiwaqt | C102: =COUNTIF(Data!$L$2:$L$20512,B102) -> 4975 | D102: =COUNTIFS(Data!$L$2:$L$20512,B102,Data!$N$2:$N$20512,"Urdu") -> 4975 | E102: =COUNTIFS(Data!$L$2:$L$20512,B102,Data!$N$2:$N$20512,"English") -> 0 | F102: =C102/$B$2 -> 0.24255278
A103: 3 | B103: Dawn News | C103: =COUNTIF(Data!$L$2:$L$20512,B103) -> 2469 | D103: =COUNTIFS(Data!$L$2:$L$20512,B103,Data!$N$2:$N$20512,"Urdu") -> 0 | E103: =COUNTIFS(Data!$L$2:$L$20512,B103,Data!$N$2:$N$20512,"English") -> 2469 | F103: =C103/$B$2 -> 0.12037443
A104: 4 | B104: City42 News | C104: =COUNTIF(Data!$L$2:$L$20512,B104) -> 2079 | D104: =COUNTIFS(Data!$L$2:$L$20512,B104,Data!$N$2:$N$20512,"Urdu") -> 2079 | E104: =COUNTIFS(Data!$L$2:$L$20512,B104,Data!$N$2:$N$20512,"English") -> 0 | F104: =C104/$B$2 -> 0.10136025
A105: 5 | B105: Express Tribune | C105: =COUNTIF(Data!$L$2:$L$20512,B105) -> 1456 | D105: =COUNTIFS(Data!$L$2:$L$20512,B105,Data!$N$2:$N$20512,"Urdu") -> 0 | E105: =COUNTIFS(Data!$L$2:$L$20512,B105,Data!$N$2:$N$20512,"English") -> 1456 | F105: =C105/$B$2 -> 0.0709863
A106: 6 | B106: Jang News | C106: =COUNTIF(Data!$L$2:$L$20512,B106) -> 1237 | D106: =COUNTIFS(Data!$L$2:$L$20512,B106,Data!$N$2:$N$20512,"Urdu") -> 1237 | E106: =COUNTIFS(Data!$L$2:$L$20512,B106,Data!$N$2:$N$20512,"English") -> 0 | F106: =C106/$B$2 -> 0.060309102
A107: 7 | B107: Daily Pakistan | C107: =COUNTIF(Data!$L$2:$L$20512,B107) -> 952 | D107: =COUNTIFS(Data!$L$2:$L$20512,B107,Data!$N$2:$N$20512,"Urdu") -> 952 | E107: =COUNTIFS(Data!$L$2:$L$20512,B107,Data!$N$2:$N$20512,"English") -> 0 | F107: =C107/$B$2 -> 0.046414119
A108: 8 | B108: Express News | C108: =COUNTIF(Data!$L$2:$L$20512,B108) -> 877 | D108: =COUNTIFS(Data!$L$2:$L$20512,B108,Data!$N$2:$N$20512,"Urdu") -> 877 | E108: =COUNTIFS(Data!$L$2:$L$20512,B108,Data!$N$2:$N$20512,"English") -> 0 | F108: =C108/$B$2 -> 0.042757545
A109: 9 | B109: Hamariweb News | C109: =COUNTIF(Data!$L$2:$L$20512,B109) -> 678 | D109: =COUNTIFS(Data!$L$2:$L$20512,B109,Data!$N$2:$N$20512,"Urdu") -> 678 | E109: =COUNTIFS(Data!$L$2:$L$20512,B109,Data!$N$2:$N$20512,"English") -> 0 | F109: =C109/$B$2 -> 0.033055434
A110: 10 | B110: The Nation | C110: =COUNTIF(Data!$L$2:$L$20512,B110) -> 276 | D110: =COUNTIFS(Data!$L$2:$L$20512,B110,Data!$N$2:$N$20512,"Urdu") -> 0 | E110: =COUNTIFS(Data!$L$2:$L$20512,B110,Data!$N$2:$N$20512,"English") -> 276 | F110: =C110/$B$2 -> 0.013456194
A111: 11 | B111: The News International | C111: =COUNTIF(Data!$L$2:$L$20512,B111) -> 193 | D111: =COUNTIFS(Data!$L$2:$L$20512,B111,Data!$N$2:$N$20512,"Urdu") -> 0 | E111: =COUNTIFS(Data!$L$2:$L$20512,B111,Data!$N$2:$N$20512,"English") -> 193 | F111: =C111/$B$2 -> 0.0094095851
A112: 12 | B112: Business Recorder | C112: =COUNTIF(Data!$L$2:$L$20512,B112) -> 151 | D112: =COUNTIFS(Data!$L$2:$L$20512,B112,Data!$N$2:$N$20512,"Urdu") -> 0 | E112: =COUNTIFS(Data!$L$2:$L$20512,B112,Data!$N$2:$N$20512,"English") -> 151 | F112: =C112/$B$2 -> 0.0073619034
... A115: 15 | B115: City42_Urdu_Crime_News_2025 | C115: =COUNTIF(Data!$L$2:$L$20512,B115) -> 1 | D115: =COUNTIFS(Data!$L$2:$L$20512,B115,Data!$N$2:$N$20512,"Urdu") -> 1 | E115: =COUNTIFS(Data!$L$2:$L$20512,B115,Data!$N$2:$N$20512,"English") -> 0 | F115: =C115/$B$2 -> 4.8754327e-05
